{
"meta":{"test_sets":[],"test_metrics":[],"learn_metrics":[{"best_value":"Min","name":"RMSE"}],"launch_mode":"Train","parameters":"","iteration_count":100,"learn_sets":["learn"],"name":"experiment"},
"iterations":[
{"learn":[1.508185421],"iteration":0,"passed_time":0.005346503317,"remaining_time":0.5293038284},
{"learn":[1.287300336],"iteration":1,"passed_time":0.007722639953,"remaining_time":0.3784093577},
{"learn":[1.105429865],"iteration":2,"passed_time":0.01054960341,"remaining_time":0.3411038436},
{"learn":[0.9606522575],"iteration":3,"passed_time":0.01258629332,"remaining_time":0.3020710396},
{"learn":[0.854140804],"iteration":4,"passed_time":0.01507865509,"remaining_time":0.2864944468},
{"learn":[0.7547181633],"iteration":5,"passed_time":0.01720583991,"remaining_time":0.2695581586},
{"learn":[0.6821068881],"iteration":6,"passed_time":0.01899307451,"remaining_time":0.2523365613},
{"learn":[0.6321363325],"iteration":7,"passed_time":0.02085006563,"remaining_time":0.2397757547},
{"learn":[0.5884322868],"iteration":8,"passed_time":0.02301609603,"remaining_time":0.2327183043},
{"learn":[0.557049696],"iteration":9,"passed_time":0.02478589526,"remaining_time":0.2230730573},
{"learn":[0.5364364232],"iteration":10,"passed_time":0.02680531762,"remaining_time":0.216879388},
{"learn":[0.5200307265],"iteration":11,"passed_time":0.0295692453,"remaining_time":0.2168411322},
{"learn":[0.5070321968],"iteration":12,"passed_time":0.04460171834,"remaining_time":0.2984884227},
{"learn":[0.49527251],"iteration":13,"passed_time":0.04650863239,"remaining_time":0.2856958847},
{"learn":[0.4856892664],"iteration":14,"passed_time":0.04826307133,"remaining_time":0.2734907375},
{"learn":[0.4760815506],"iteration":15,"passed_time":0.05010978218,"remaining_time":0.2630763564},
{"learn":[0.469988516],"iteration":16,"passed_time":0.05248941371,"remaining_time":0.2562718434},
{"learn":[0.4621708414],"iteration":17,"passed_time":0.05445040938,"remaining_time":0.2480518649},
{"learn":[0.4583562708],"iteration":18,"passed_time":0.05655419757,"remaining_time":0.2410994738},
{"learn":[0.4536389153],"iteration":19,"passed_time":0.05895777631,"remaining_time":0.2358311052},
{"learn":[0.4506137735],"iteration":20,"passed_time":0.06120967551,"remaining_time":0.2302649698},
{"learn":[0.4477988069],"iteration":21,"passed_time":0.06294161058,"remaining_time":0.2231566193},
{"learn":[0.4435574047],"iteration":22,"passed_time":0.06531685145,"remaining_time":0.2186694592},
{"learn":[0.4411536931],"iteration":23,"passed_time":0.06732394049,"remaining_time":0.2131924782},
{"learn":[0.4373114985],"iteration":24,"passed_time":0.0696589275,"remaining_time":0.2089767825},
{"learn":[0.434566045],"iteration":25,"passed_time":0.07226467131,"remaining_time":0.2056763722},
{"learn":[0.4309405921],"iteration":26,"passed_time":0.07412905702,"remaining_time":0.200423006},
{"learn":[0.4285888844],"iteration":27,"passed_time":0.0759485943,"remaining_time":0.1952963853},
{"learn":[0.4242337139],"iteration":28,"passed_time":0.07819637538,"remaining_time":0.1914462983},
{"learn":[0.4225568901],"iteration":29,"passed_time":0.08045756289,"remaining_time":0.1877343134},
{"learn":[0.4200543715],"iteration":30,"passed_time":0.08223105038,"remaining_time":0.1830304025},
{"learn":[0.4178716101],"iteration":31,"passed_time":0.08431000862,"remaining_time":0.1791587683},
{"learn":[0.4154020484],"iteration":32,"passed_time":0.0870089111,"remaining_time":0.1766544559},
{"learn":[0.4129253736],"iteration":33,"passed_time":0.08952800207,"remaining_time":0.1737896511},
{"learn":[0.4106385771],"iteration":34,"passed_time":0.09206723175,"remaining_time":0.1709820018},
{"learn":[0.4078318631],"iteration":35,"passed_time":0.09481682367,"remaining_time":0.1685632421},
{"learn":[0.4055134647],"iteration":36,"passed_time":0.09656818654,"remaining_time":0.1644269122},
{"learn":[0.4044738067],"iteration":37,"passed_time":0.09885179425,"remaining_time":0.1612845064},
{"learn":[0.4028061159],"iteration":38,"passed_time":0.1006353351,"remaining_time":0.1574039856},
{"learn":[0.4003895132],"iteration":39,"passed_time":0.1023861869,"remaining_time":0.1535792804},
{"learn":[0.3985056628],"iteration":40,"passed_time":0.1042929662,"remaining_time":0.1500801221},
{"learn":[0.3973548218],"iteration":41,"passed_time":0.1061735774,"remaining_time":0.1466206545},
{"learn":[0.3953491166],"iteration":42,"passed_time":0.1084923449,"remaining_time":0.143815434},
{"learn":[0.392803612],"iteration":43,"passed_time":0.1111271591,"remaining_time":0.1414345661},
{"learn":[0.3920051013],"iteration":44,"passed_time":0.113449412,"remaining_time":0.1386603924},
{"learn":[0.3903578295],"iteration":45,"passed_time":0.115306355,"remaining_time":0.1353596341},
{"learn":[0.3878009384],"iteration":46,"passed_time":0.1173137461,"remaining_time":0.132289969},
{"learn":[0.3859048942],"iteration":47,"passed_time":0.1196288369,"remaining_time":0.1295979067},
{"learn":[0.3845864946],"iteration":48,"passed_time":0.122486303,"remaining_time":0.1274857439},
{"learn":[0.3815960482],"iteration":49,"passed_time":0.1249740993,"remaining_time":0.1249740993},
{"learn":[0.3799382528],"iteration":50,"passed_time":0.1270053244,"remaining_time":0.1220247235},
{"learn":[0.3764999556],"iteration":51,"passed_time":0.1302291057,"remaining_time":0.1202114822},
{"learn":[0.3743957613],"iteration":52,"passed_time":0.1331294684,"remaining_time":0.1180582078},
{"learn":[0.3724578583],"iteration":53,"passed_time":0.1392238938,"remaining_time":0.1185981317},
{"learn":[0.3709031921],"iteration":54,"passed_time":0.1419191676,"remaining_time":0.1161156826},
{"learn":[0.3692431849],"iteration":55,"passed_time":0.1437452778,"remaining_time":0.1129427183},
{"learn":[0.368360935],"iteration":56,"passed_time":0.1458326932,"remaining_time":0.110014137},
{"learn":[0.3668193454],"iteration":57,"passed_time":0.1477959639,"remaining_time":0.1070246635},
{"learn":[0.3654747995],"iteration":58,"passed_time":0.1497058092,"remaining_time":0.1040328505},
{"learn":[0.3644720114],"iteration":59,"passed_time":0.1519003959,"remaining_time":0.1012669306},
{"learn":[0.3627802378],"iteration":60,"passed_time":0.1545008408,"remaining_time":0.09877922608},
{"learn":[0.3614205141],"iteration":61,"passed_time":0.1570413315,"remaining_time":0.09625113863},
{"learn":[0.3579873928],"iteration":62,"passed_time":0.158878273,"remaining_time":0.09330946195},
{"learn":[0.3567225768],"iteration":63,"passed_time":0.1609082853,"remaining_time":0.09051091047},
{"learn":[0.3561693292],"iteration":64,"passed_time":0.1630514862,"remaining_time":0.0877969541},
{"learn":[0.3554311934],"iteration":65,"passed_time":0.1650177327,"remaining_time":0.08500913503},
{"learn":[0.3547053171],"iteration":66,"passed_time":0.1669401328,"remaining_time":0.0822242445},
{"learn":[0.3535663383],"iteration":67,"passed_time":0.1689576704,"remaining_time":0.07950949197},
{"learn":[0.3515593802],"iteration":68,"passed_time":0.1711143714,"remaining_time":0.07687747123},
{"learn":[0.3501277446],"iteration":69,"passed_time":0.1729594591,"remaining_time":0.07412548247},
{"learn":[0.3496352584],"iteration":70,"passed_time":0.1760335999,"remaining_time":0.07190104783},
{"learn":[0.3475252066],"iteration":71,"passed_time":0.1803733263,"remaining_time":0.07014518245},
{"learn":[0.3466707555],"iteration":72,"passed_time":0.1821947478,"remaining_time":0.0673870985},
{"learn":[0.3459529467],"iteration":73,"passed_time":0.1841093224,"remaining_time":0.06468705923},
{"learn":[0.3453349481],"iteration":74,"passed_time":0.185948288,"remaining_time":0.06198276267},
{"learn":[0.3428764856],"iteration":75,"passed_time":0.1879167985,"remaining_time":0.0593421469},
{"learn":[0.3411561527],"iteration":76,"passed_time":0.1897553939,"remaining_time":0.05668018258},
{"learn":[0.340495305],"iteration":77,"passed_time":0.1923097398,"remaining_time":0.05424120867},
{"learn":[0.3390092861],"iteration":78,"passed_time":0.1949587024,"remaining_time":0.05182446519},
{"learn":[0.3380365185],"iteration":79,"passed_time":0.197166956,"remaining_time":0.049291739},
{"learn":[0.3376341287],"iteration":80,"passed_time":0.19907612,"remaining_time":0.04669686765},
{"learn":[0.3372401374],"iteration":81,"passed_time":0.2012801453,"remaining_time":0.04418344653},
{"learn":[0.3369550306],"iteration":82,"passed_time":0.2036753976,"remaining_time":0.04171664771},
{"learn":[0.3366757232],"iteration":83,"passed_time":0.2061890168,"remaining_time":0.03927409844},
{"learn":[0.3363899319],"iteration":84,"passed_time":0.2349627016,"remaining_time":0.04146400617},
{"learn":[0.3350884153],"iteration":85,"passed_time":0.2396065271,"remaining_time":0.03900571372},
{"learn":[0.3342791145],"iteration":86,"passed_time":0.2421597589,"remaining_time":0.03618479156},
{"learn":[0.332406172],"iteration":87,"passed_time":0.2450084953,"remaining_time":0.03341024936},
{"learn":[0.3312388138],"iteration":88,"passed_time":0.2472372814,"remaining_time":0.0305574168},
{"learn":[0.3296636066],"iteration":89,"passed_time":0.250170823,"remaining_time":0.02779675811},
{"learn":[0.3273246621],"iteration":90,"passed_time":0.2531785428,"remaining_time":0.0250396361},
{"learn":[0.3267625749],"iteration":91,"passed_time":0.2554711643,"remaining_time":0.02221488385},
{"learn":[0.3264192998],"iteration":92,"passed_time":0.2577143964,"remaining_time":0.01939785779},
{"learn":[0.3257466328],"iteration":93,"passed_time":0.2601027161,"remaining_time":0.01660230103},
{"learn":[0.3253489836],"iteration":94,"passed_time":0.262106224,"remaining_time":0.01379506442},
{"learn":[0.3246051694],"iteration":95,"passed_time":0.2641240022,"remaining_time":0.01100516676},
{"learn":[0.3241121954],"iteration":96,"passed_time":0.2666884596,"remaining_time":0.008248096688},
{"learn":[0.3226335198],"iteration":97,"passed_time":0.26925495,"remaining_time":0.00549499898},
{"learn":[0.3206134836],"iteration":98,"passed_time":0.2715582105,"remaining_time":0.002743012227},
{"learn":[0.3200496962],"iteration":99,"passed_time":0.2737250324,"remaining_time":0}
]}